cupylma/__init__.py
cupylma/config.py
cupylma/lma.py
cupylma/sliced_tensor.py
cupylma-0.1.2.dist-info/licenses/LICENSE
cupylma-0.1.2.dist-info/METADATA
cupylma-0.1.2.dist-info/WHEEL
cupylma-0.1.2.dist-info/top_level.txt
cupylma-0.1.2.dist-info/RECORD
