Metadata-Version: 2.4
Name: cupylma
Version: 0.1.2
Summary: cuPyLMA: a Multi-GPU Levenberg-Marquardt Optimizer powered by cuPyNumeric
Author-email: Xianghao Wang <wang.xianghao@outlook.com>
Project-URL: Homepage, https://github.com/wang-xianghao/cuPyLMA
Project-URL: Issues, https://github.com/wang-xianghao/cuPyLMA/issues
Classifier: Programming Language :: Python :: 3
Requires-Python: >=3.8
License-File: LICENSE
Requires-Dist: nvidia-cupynumeric
Requires-Dist: torch
Requires-Dist: torchvision
Requires-Dist: nvtx
Dynamic: license-file
